xmodel_dynamo/__init__.py
xmodel_dynamo/api.py
xmodel_dynamo/client.py
xmodel_dynamo/common_types.py
xmodel_dynamo/db.py
xmodel_dynamo/errors.py
xmodel_dynamo/fields.py
xmodel_dynamo/meta.json
xmodel_dynamo/model.py
xmodel_dynamo/resources.py
xmodel_dynamo/structure.py
xmodel_dynamo/utils.py
xmodel_dynamo-0.1.1.dist-info/METADATA
xmodel_dynamo-0.1.1.dist-info/WHEEL
xmodel_dynamo-0.1.1.dist-info/RECORD
