Metadata-Version: 2.1
Name: xmodel-dynamo
Version: 0.1.1
Summary: Use dynamo with xmodel objects.
Home-page: https://github.com/xyngular/py-xmodel-dynamo
Author: Josh Orr
Author-email: josh@orr.blue
Requires-Python: >=3.8,<3.9
Classifier: License :: OSI Approved :: The Unlicense (Unlicense)
Classifier: Programming Language :: Python :: 3
Classifier: Programming Language :: Python :: 3.8
Classifier: Topic :: Software Development :: Libraries :: Python Modules
Requires-Dist: boto3 (>=1.17.54,<2.0.0)
Requires-Dist: ciso8601 (>=2.3.0,<3.0.0)
Requires-Dist: xboto (>=1.0.2,<2.0.0)
Requires-Dist: xcon (>=0.4.0,<0.5.0)
Requires-Dist: xinject (>=1.4.0,<2.0.0)
Requires-Dist: xloop (>=1.0.1,<2.0.0)
Requires-Dist: xmodel (>=0.3.0,<0.4.0)
Requires-Dist: xsentinels (>=1.2.1,<2.0.0)
Requires-Dist: xsettings (>=1.3.0,<2.0.0)
Requires-Dist: xurls (>=0.2.0,<0.3.0)
Project-URL: Repository, https://github.com/xyngular/py-xmodel-dynamo
